tracdap/ext/http/__init__.py
tracdap/ext/http/http_plugin.py
tracdap_ext_http-0.10.0.dev21.dist-info/licenses/LICENSE
tracdap_ext_http-0.10.0.dev21.dist-info/METADATA
tracdap_ext_http-0.10.0.dev21.dist-info/WHEEL
tracdap_ext_http-0.10.0.dev21.dist-info/top_level.txt
tracdap_ext_http-0.10.0.dev21.dist-info/RECORD
