Metadata-Version: 2.4
Name: tracdap-ext-http
Version: 0.10.0.dev21
Summary: An extension for TRAC D.A.P. that lets models connect to HTTP endpoints
Author-email: Martin Traverse <martin@fintrac.co.uk>
License-Expression: Apache-2.0
Project-URL: Homepage, https://tracdap.finos.org/
Project-URL: Documentation, https://tracdap.readthedocs.io/
Project-URL: Source Code, https://github.com/finos/tracdap
Project-URL: Issue Tracker, https://github.com/finos/tracdap/issues
Classifier: Operating System :: OS Independent
Classifier: Programming Language :: Python :: 3
Classifier: Programming Language :: Python :: 3.10
Classifier: Programming Language :: Python :: 3.11
Classifier: Programming Language :: Python :: 3.12
Classifier: Programming Language :: Python :: 3.13
Classifier: Intended Audience :: Developers
Classifier: Intended Audience :: End Users/Desktop
Classifier: Intended Audience :: Financial and Insurance Industry
Classifier: Topic :: Office/Business
Classifier: Topic :: Office/Business :: Financial
Classifier: Topic :: Software Development
Classifier: Topic :: Software Development :: Libraries :: Application Frameworks
Classifier: Topic :: Software Development :: Libraries :: Python Modules
Requires-Python: >=3.10
License-File: LICENSE
Requires-Dist: tracdap-runtime>=0.10.0-beta.1
Dynamic: license-file
